Metadata-Version: 2.1
Name: datetime-glob
Version: 1.0.8
Summary: Parse date/time from paths using glob wildcard pattern intertwined with date/time format
Home-page: https://github.com/Parquery/datetime-glob
Author: Marko Ristin
Author-email: marko.ristin@gmail.com
License: UNKNOWN
Keywords: date time datetime parse glob pattern strptime wildcards
Platform: UNKNOWN
Classifier: Development Status :: 5 - Production/Stable
Classifier: Intended Audience :: Developers
Classifier: License :: OSI Approved :: MIT License
Classifier: Programming Language :: Python :: 3.5
Classifier: Programming Language :: Python :: 3.6
Classifier: Programming Language :: Python :: 3.7
Classifier: Programming Language :: Python :: 3.8
Requires-Python: >=3.5
Provides-Extra: dev
